pytest_multihost/__init__.py
pytest_multihost/config.py
pytest_multihost/host.py
pytest_multihost/plugin.py
pytest_multihost/transport.py
pytest_multihost/util.py
pytest_multihost-3.0.dist-info/DESCRIPTION.rst
pytest_multihost-3.0.dist-info/METADATA
pytest_multihost-3.0.dist-info/RECORD
pytest_multihost-3.0.dist-info/WHEEL
pytest_multihost-3.0.dist-info/entry_points.txt
pytest_multihost-3.0.dist-info/metadata.json
pytest_multihost-3.0.dist-info/top_level.txt
