Metadata-Version: 2.0
Name: pytest-multihost
Version: 3.0
Summary: Utility for writing multi-host tests for pytest
Home-page: https://pagure.io/python-pytest-multihost
Author: Petr Viktorin
Author-email: pviktori@redhat.com
License: GPL
Platform: UNKNOWN
Classifier: Development Status :: 4 - Beta
Classifier: License :: OSI Approved :: GNU General Public License v3 or later (GPLv3+)
Classifier: Operating System :: POSIX
Classifier: Framework :: Pytest
Classifier: Programming Language :: Python
Classifier: Programming Language :: Python :: 2.6
Classifier: Programming Language :: Python :: 2.7
Classifier: Programming Language :: Python :: 3
Classifier: Topic :: Software Development :: Quality Assurance
Requires-Dist: pytest (>=2.4.0)
